ontic/__init__.py
ontic/core.py
ontic/meta.py
ontic/property.py
ontic/schema.py
ontic/type.py
ontic/validation_exception.py
ontic-1.0.0.dist-info/LICENSE
ontic-1.0.0.dist-info/METADATA
ontic-1.0.0.dist-info/WHEEL
ontic-1.0.0.dist-info/top_level.txt
ontic-1.0.0.dist-info/RECORD
