Metadata-Version: 2.1
Name: ontic
Version: 1.0.0
Summary: Qualities and Quantities are the stuff of Objects.
Home-page: https://github.com/neoinsanity/ontic
Author: Raul Gonzalez
Author-email: mindbender@gmail.com
License: Apache License 2.0
Platform: UNKNOWN
Classifier: Development Status :: 3 - Alpha
Classifier: Intended Audience :: Developers
Classifier: License :: OSI Approved :: Apache Software License
Classifier: Operating System :: OS Independent
Classifier: Programming Language :: Python :: 3.5
Classifier: Topic :: Software Development
License-File: LICENSE
